message_overrides.py
pylint2codeclimate.py
pylint2codeclimate-1.3.dist-info/METADATA
pylint2codeclimate-1.3.dist-info/RECORD
pylint2codeclimate-1.3.dist-info/WHEEL
pylint2codeclimate-1.3.dist-info/top_level.txt
