Metadata-Version: 2.1
Name: pylint2codeclimate
Version: 1.3
Summary: pylint reporter class to export results in codeclimate format
Home-page: https://gitlab.com/alelec/pylint2codeclimate
Author: Andrew Leech
Author-email: andrew@alelec.net
License: MIT
Platform: UNKNOWN
